OmnicommSun/__init__.py
OmnicommSun/omincomm_sun.py
OmnicommSun-0.1.1.dist-info/METADATA
OmnicommSun-0.1.1.dist-info/WHEEL
OmnicommSun-0.1.1.dist-info/top_level.txt
OmnicommSun-0.1.1.dist-info/RECORD
