Metadata-Version: 2.1
Name: OmnicommSun
Version: 0.1.1
Summary: test
Home-page: https://github.com/SeAllexUnder/OmnicommSun
Author: SeAllexUnder
Author-email: sun5038@yandex.ru
Project-URL: GitHub, https://github.com/SeAllexUnder/OmnicommSun
Keywords: omnicomm
Classifier: Programming Language :: Python :: 3.11
Classifier: License :: OSI Approved :: MIT License
Classifier: Operating System :: OS Independent
Requires-Python: >=3.6
Requires-Dist: requests >=2.25.1
